truthbrush/__init__.py
truthbrush/api.py
truthbrush/cli.py
truthbrush-0.2.5.dist-info/METADATA
truthbrush-0.2.5.dist-info/WHEEL
truthbrush-0.2.5.dist-info/entry_points.txt
truthbrush-0.2.5.dist-info/licenses/LICENSE
truthbrush-0.2.5.dist-info/RECORD
