Metadata-Version: 2.4
Name: truthbrush
Version: 0.2.5
Summary: API client for Truth Social
License: Apache 2.0
License-File: LICENSE
Author: R. Miles McCain
Author-email: github@sendmiles.email
Requires-Python: >=3.10,<4.0
Classifier: License :: Other/Proprietary License
Classifier: Programming Language :: Python :: 3
Classifier: Programming Language :: Python :: 3.10
Classifier: Programming Language :: Python :: 3.11
Classifier: Programming Language :: Python :: 3.12
Classifier: Programming Language :: Python :: 3.13
Classifier: Programming Language :: Python :: 3.14
Requires-Dist: click (>=8.1.0,<9.0.0)
Requires-Dist: curl_cffi (>=0.14.0,<0.15.0)
Requires-Dist: loguru (>=0.7.0,<0.8.0)
Requires-Dist: python-dateutil (>=2.9.0,<3.0.0)
Requires-Dist: python-dotenv (>=1.0.1,<2.0.0)
